she_logging/__init__.py
she_logging/fastapi_request_id.py
she_logging/gunicorn_logger.py
she_logging/logging.py
she_logging/py.typed
she_logging/request_id.py
she_logging-1.4.1.dist-info/entry_points.txt
she_logging-1.4.1.dist-info/LICENSE.md
she_logging-1.4.1.dist-info/WHEEL
she_logging-1.4.1.dist-info/METADATA
she_logging-1.4.1.dist-info/RECORD
